structer/__init__.py
structer/errors.py
structer/field.py
structer/py.typed
structer/struct.py
structer/fieldtypes/base.py
structer/fieldtypes/char.py
structer/fieldtypes/string.py
structer-0.3.0.dist-info/LICENSE
structer-0.3.0.dist-info/METADATA
structer-0.3.0.dist-info/WHEEL
structer-0.3.0.dist-info/top_level.txt
structer-0.3.0.dist-info/RECORD
