Metadata-Version: 2.1
Name: structer
Version: 0.3.0
Summary: Structer is a structurer written in Python based on C language structs.
Author-email: Lelzin λ <d3cryptofc@gmail.com>
License: MIT License
Project-URL: Repository, https://github.com/d3cryptofc/structer
Classifier: Programming Language :: Python :: 3
Classifier: Programming Language :: Python :: 3.9
Classifier: Programming Language :: Python :: 3.10
Classifier: Programming Language :: Python :: 3.11
Classifier: Programming Language :: Python :: 3.12
Requires-Python: >=3.9
License-File: LICENSE
